<?xml version="1.0" encoding="UTF-8" standalone="no" ?>
<InspData>

  <ConfigInfo>
    <Inspector>MV-6DL</Inspector>
    <DefectPath>D:/PcbModel</DefectPath>
    <IsSaveOverKill>TRUE</IsSaveOverKill>
    <UserID>master</UserID>
  </ConfigInfo>

  <BoardInfo>
    <Model>12113504-00-A0-B</Model>
    <SerialNo>0423118036521</SerialNo>
    <RepSerialNo>0423118036522</RepSerialNo>
    <BoardSide>0</BoardSide>
    <CarrierID>None</CarrierID>
    <LotID></LotID>
    <ComputerName>MV-6DLOMNI</ComputerName>
    <BoardCount>1012</BoardCount>
    <ModuleCount>2</ModuleCount>
    <InspStartTime>20180804;102215</InspStartTime>
    <IsGood>0</IsGood>
    <IsInspectGood>0</IsInspectGood>
  </BoardInfo>

  <DefectInfo>
    <InspStartTime>2018-08-04 10:22:15</InspStartTime>
    <InspEndTime>2018-08-04 10:22:21</InspEndTime>
    <OperatorEndTime>2018-08-04 10:22:21</OperatorEndTime>
    <RepairEndTime>2018-08-04 10:22:21</RepairEndTime>
    <InspResult>1</InspResult>
    <BoardSide>0</BoardSide>
  </DefectInfo>

  <DefectCount>
    <Mounting>0</Mounting>
    <Solder>0</Solder>
    <Bridge>0</Bridge>
    <OCR>0</OCR>
    <Binary>0</Binary>
    <Color>1</Color>
    <Height>0</Height>
    <LiftedLead>0</LiftedLead>
    <ChipChecker>0</ChipChecker>
    <ResistorColorChecker>0</ResistorColorChecker>
    <BridgeOffset>0</BridgeOffset>
    <ChipColorInsp>0</ChipColorInsp>
    <ICSolder>0</ICSolder>
    <ContoursFind>0</ContoursFind>
  </DefectCount>

  <InspCount>
    <Part>257</Part>
    <Frame>5</Frame>
    <Window>1169</Window>
    <Mounting>322</Mounting>
    <Solder>509</Solder>
    <Bridge>32</Bridge>
    <OCR>0</OCR>
    <Binary>0</Binary>
    <Color>218</Color>
    <Height>88</Height>
    <LiftedLead>0</LiftedLead>
    <ChipChecker>0</ChipChecker>
    <ResistorColorChecker>0</ResistorColorChecker>
    <BridgeOffset>0</BridgeOffset>
    <ChipColorInsp>0</ChipColorInsp>
    <ICSolder>0</ICSolder>
    <ContoursFind>0</ContoursFind>
    <PinHole>0</PinHole>
    <SkipInfo>0</SkipInfo>
  </InspCount>

  <ModuleResult>
    <Module IsSkiped="0" ModuleId="1" Result="0"/>
  </ModuleResult>

  <Defect>
    <Overkill>0</Overkill>
    <DefectTypeString>WrongPart</DefectTypeString>
    <ModuleId>1</ModuleId>
    <RefId>R764</RefId>
    <FrameId>1</FrameId>
    <WindowId>2</WindowId>
    <IsImportantWindow>0</IsImportantWindow>
    <PartNumber>11323283-00</PartNumber>
    <PartID>54842189-DBA4-4219-86B1-C8FB8598570B</PartID>
    <WindowType>8</WindowType>
    <ViewType>1</ViewType>
    <PartGrabType>-1</PartGrabType>
    <Reviewed>0</Reviewed>
    <GroupDefectInfo>1</GroupDefectInfo>
    <VirtualRefID>VBA69D126-98F5-4172-8E42-265CA9D0FA65</VirtualRefID>
    <WindowRefID>_CLR_194_</WindowRefID>
    <ResultValue>0.000000</ResultValue>
    <CameraNo>-1</CameraNo>
    <PartRect X1="1860" X2="1860" X3="1892" X4="1892" Y1="2132" Y2="2050" Y3="2050" Y4="2132"/>
    <WindowRect X1="1870" X2="1870" X3="1880" X4="1880" Y1="2098" Y2="2087" Y3="2087" Y4="2098"/>
    <FrameRect X1="332456" X2="371500" X3="371500" X4="332456" Y1="44679" Y2="44679" Y3="83770" Y4="83770"/>
    <DefectRect X1="351167" X2="351271" X3="351271" X4="351167" Y1="62762" Y2="62762" Y3="62854" Y4="62854"/>
    <AngleOffset>0.00</AngleOffset>
    <Offset X="5" Y="-3"/>
    <Viewer3DMaxRange>0</Viewer3DMaxRange>
    <ViewerDirection>5</ViewerDirection>
    <WindowAngle>90</WindowAngle>
    <DefectType>13</DefectType>
    <Defect3DType>13</Defect3DType>
    <PassDefectType/>
    <PassDefect3DType/>
    <DefectPins/>
    <OverKillPins/>
  </Defect>

</InspData>
