<?xml version="1.0" encoding="UTF-8" standalone="no" ?>
<InspData>

  <ConfigInfo>
    <Inspector>MV-6DL</Inspector>
    <DefectPath>D:/PcbModel</DefectPath>
    <IsSaveOverKill>TRUE</IsSaveOverKill>
    <UserID>master</UserID>
  </ConfigInfo>

  <BoardInfo>
    <Model>12113504-00-A0-B</Model>
    <SerialNo>0423118036441</SerialNo>
    <RepSerialNo>0423118036442</RepSerialNo>
    <BoardSide>0</BoardSide>
    <CarrierID>None</CarrierID>
    <LotID/>
    <ComputerName>MV-6DLOMNI</ComputerName>
    <BoardCount>1086</BoardCount>
    <ModuleCount>2</ModuleCount>
    <InspStartTime>20180804;105614</InspStartTime>
    <IsGood>1</IsGood>
    <IsInspectGood>0</IsInspectGood>
  </BoardInfo>

  <DefectInfo>
    <InspStartTime>2018-08-04 10:56:14</InspStartTime>
    <InspEndTime>2018-08-04 10:56:20</InspEndTime>
    <OperatorEndTime>2018-08-04 10:56:20</OperatorEndTime>
    <RepairEndTime>2018-08-04 10:56:54</RepairEndTime>
    <InspResult>1</InspResult>
    <BoardSide>0</BoardSide>
  </DefectInfo>

  <DefectCount>
    <Mounting>0</Mounting>
    <Solder>1</Solder>
    <Bridge>0</Bridge>
    <OCR>0</OCR>
    <Binary>0</Binary>
    <Color>0</Color>
    <Height>0</Height>
    <LiftedLead>0</LiftedLead>
    <ChipChecker>0</ChipChecker>
    <ResistorColorChecker>0</ResistorColorChecker>
    <BridgeOffset>0</BridgeOffset>
    <ChipColorInsp>0</ChipColorInsp>
    <ICSolder>0</ICSolder>
    <ContoursFind>0</ContoursFind>
  </DefectCount>

  <InspCount>
    <Part>257</Part>
    <Frame>5</Frame>
    <Window>1169</Window>
    <Mounting>322</Mounting>
    <Solder>509</Solder>
    <Bridge>32</Bridge>
    <OCR>0</OCR>
    <Binary>0</Binary>
    <Color>218</Color>
    <Height>88</Height>
    <LiftedLead>0</LiftedLead>
    <ChipChecker>0</ChipChecker>
    <ResistorColorChecker>0</ResistorColorChecker>
    <BridgeOffset>0</BridgeOffset>
    <ChipColorInsp>0</ChipColorInsp>
    <ICSolder>0</ICSolder>
    <ContoursFind>0</ContoursFind>
    <PinHole>0</PinHole>
    <SkipInfo>0</SkipInfo>
  </InspCount>

  <ModuleResult>
    <Module IsSkiped="0" ModuleId="1" Result="0"/>
  </ModuleResult>

  <Defect>
    <Overkill>1</Overkill>
    <DefectTypeString>InsufficientSolder</DefectTypeString>
    <ModuleId>1</ModuleId>
    <RefId>C6</RefId>
    <FrameId>2</FrameId>
    <WindowId>2</WindowId>
    <IsImportantWindow>0</IsImportantWindow>
    <PartNumber>11879086-00</PartNumber>
    <PartID>F6E9470E-9CBC-463f-BF5E-75CCEBD15BBB</PartID>
    <WindowType>2</WindowType>
    <ViewType>2</ViewType>
    <PartGrabType>-1</PartGrabType>
    <Reviewed>2</Reviewed>
    <GroupDefectInfo>1</GroupDefectInfo>
    <VirtualRefID>V5B8D26EA-F448-4037-A72E-06B5275BD5A3</VirtualRefID>
    <WindowRefID>_SLD_636_</WindowRefID>
    <ResultValue>0.000000</ResultValue>
    <CameraNo>-1</CameraNo>
    <PartRect X1="1848" X2="1848" X3="1749" X4="1749" Y1="1860" Y2="2067" Y3="2067" Y4="1860"/>
    <WindowRect X1="1846" X2="1846" X3="1753" X4="1753" Y1="1860" Y2="1885" Y3="1885" Y4="1860"/>
    <FrameRect X1="358016" X2="397059" X3="397059" X4="358016" Y1="41642" Y2="41642" Y3="80733" Y4="80733"/>
    <DefectRect X1="375902" X2="376148" X3="376148" X4="375902" Y1="61511" Y2="61511" Y3="62449" Y4="62449"/>
    <AngleOffset>0.00</AngleOffset>
    <Offset X="-4" Y="13"/>
    <DefectPos X1="1846" X2="1846" X3="1752" X4="1752" Y1="1860" Y2="1885" Y3="1885" Y4="1860"/>
    <Viewer3DMaxRange>0</Viewer3DMaxRange>
    <ViewerDirection>5</ViewerDirection>
    <WindowAngle>270</WindowAngle>
    <DefectType></DefectType>
    <Defect3DType></Defect3DType>
    <PassDefectType>5</PassDefectType>
    <PassDefect3DType/>
    <DefectPins></DefectPins>
    <OverKillPins></OverKillPins>
    <IsChanged>1</IsChanged></Defect>

</InspData>
