<?xml version="1.0" encoding="UTF-8" standalone="no" ?>
<InspData>

  <ConfigInfo>
    <Inspector>MV-6DL</Inspector>
    <DefectPath>D:/PcbModel</DefectPath>
    <IsSaveOverKill>TRUE</IsSaveOverKill>
    <UserID>master</UserID>
  </ConfigInfo>

  <BoardInfo>
    <Model>12113504-00-A0-B</Model>
    <SerialNo>0423118036564</SerialNo>
    <RepSerialNo>0423118036564</RepSerialNo>
    <BoardSide>0</BoardSide>
    <CarrierID>None</CarrierID>
    <LotID/>
    <ComputerName>MV-6DLOMNI</ComputerName>
    <BoardCount>998</BoardCount>
    <ModuleCount>2</ModuleCount>
    <InspStartTime>20180804;100306</InspStartTime>
    <IsGood>1</IsGood>
    <IsInspectGood>0</IsInspectGood>
  </BoardInfo>

  <DefectInfo>
    <InspStartTime>2018-08-04 10:03:06</InspStartTime>
    <InspEndTime>2018-08-04 10:03:09</InspEndTime>
    <OperatorEndTime>2018-08-04 10:03:12</OperatorEndTime>
    <RepairEndTime>2018-08-04 10:04:01</RepairEndTime>
    <InspResult>1</InspResult>
    <BoardSide>0</BoardSide>
  </DefectInfo>

  <DefectCount>
    <Mounting>0</Mounting>
    <Solder>0</Solder>
    <Bridge>0</Bridge>
    <OCR>0</OCR>
    <Binary>0</Binary>
    <Color>1</Color>
    <Height>0</Height>
    <LiftedLead>0</LiftedLead>
    <ChipChecker>0</ChipChecker>
    <ResistorColorChecker>0</ResistorColorChecker>
    <BridgeOffset>0</BridgeOffset>
    <ChipColorInsp>0</ChipColorInsp>
    <ICSolder>0</ICSolder>
    <ContoursFind>0</ContoursFind>
  </DefectCount>

  <InspCount>
    <Part>257</Part>
    <Frame>5</Frame>
    <Window>1169</Window>
    <Mounting>322</Mounting>
    <Solder>509</Solder>
    <Bridge>32</Bridge>
    <OCR>0</OCR>
    <Binary>0</Binary>
    <Color>218</Color>
    <Height>88</Height>
    <LiftedLead>0</LiftedLead>
    <ChipChecker>0</ChipChecker>
    <ResistorColorChecker>0</ResistorColorChecker>
    <BridgeOffset>0</BridgeOffset>
    <ChipColorInsp>0</ChipColorInsp>
    <ICSolder>0</ICSolder>
    <ContoursFind>0</ContoursFind>
    <PinHole>0</PinHole>
    <SkipInfo>0</SkipInfo>
  </InspCount>

  <ModuleResult>
    <Module IsSkiped="0" ModuleId="0" Result="0"/>
  </ModuleResult>

  <Defect>
    <Overkill>1</Overkill>
    <DefectTypeString>WrongPart</DefectTypeString>
    <ModuleId>0</ModuleId>
    <RefId>R585</RefId>
    <FrameId>2</FrameId>
    <WindowId>2</WindowId>
    <IsImportantWindow>0</IsImportantWindow>
    <PartNumber>10458183-00</PartNumber>
    <PartID>DB1669E0-D35C-4370-829A-C07E75F48DF7</PartID>
    <WindowType>8</WindowType>
    <ViewType>1</ViewType>
    <PartGrabType>-1</PartGrabType>
    <Reviewed>2</Reviewed>
    <GroupDefectInfo>1</GroupDefectInfo>
    <VirtualRefID>V46874653-D434-41fb-9437-A58DC4D6BC4D</VirtualRefID>
    <WindowRefID>_CLR_97_</WindowRefID>
    <ResultValue>0.000000</ResultValue>
    <CameraNo>-1</CameraNo>
    <PartRect X1="2184" X2="2310" X3="2310" X4="2184" Y1="2796" Y2="2796" Y3="2846" Y4="2846"/>
    <WindowRect X1="2239" X2="2254" X3="2254" X4="2239" Y1="2814" Y2="2814" Y3="2829" Y4="2829"/>
    <FrameRect X1="447087" X2="486130" X3="486130" X4="447087" Y1="41633" Y2="41633" Y3="80724" Y4="80724"/>
    <DefectRect X1="469488" X2="469631" X3="469631" X4="469488" Y1="52394" Y2="52394" Y3="52544" Y4="52544"/>
    <AngleOffset>0.00</AngleOffset>
    <Offset X="-2" Y="-7"/>
    <Viewer3DMaxRange>0</Viewer3DMaxRange>
    <ViewerDirection>5</ViewerDirection>
    <WindowAngle>0</WindowAngle>
    <DefectType></DefectType>
    <Defect3DType></Defect3DType>
    <PassDefectType>13</PassDefectType>
    <PassDefect3DType/>
    <DefectPins></DefectPins>
    <OverKillPins></OverKillPins>
    <IsChanged>1</IsChanged></Defect>

</InspData>
