<?xml version="1.0" encoding="UTF-8" standalone="no" ?>
<InspData>

  <ConfigInfo>
    <Inspector>MV-6DL</Inspector>
    <DefectPath>D:/PcbModel</DefectPath>
    <IsSaveOverKill>TRUE</IsSaveOverKill>
    <UserID>master</UserID>
  </ConfigInfo>

  <BoardInfo>
    <Model>12113504-00-A0-B</Model>
    <SerialNo>0422918036530</SerialNo>
    <RepSerialNo>0422918036531</RepSerialNo>
    <BoardSide>0</BoardSide>
    <CarrierID>None</CarrierID>
    <LotID/>
    <ComputerName>MV-6DLOMNI</ComputerName>
    <BoardCount>76</BoardCount>
    <ModuleCount>2</ModuleCount>
    <InspStartTime>20180727;111529</InspStartTime>
    <IsGood>1</IsGood>
    <IsInspectGood>0</IsInspectGood>
  </BoardInfo>

  <DefectInfo>
    <InspStartTime>2018-07-27 11:15:29</InspStartTime>
    <InspEndTime>2018-07-27 11:15:34</InspEndTime>
    <OperatorEndTime>2018-07-27 11:15:35</OperatorEndTime>
    <RepairEndTime>2018-07-27 11:15:54</RepairEndTime>
    <InspResult>1</InspResult>
    <BoardSide>0</BoardSide>
  </DefectInfo>

  <DefectCount>
    <Mounting>0</Mounting>
    <Solder>0</Solder>
    <Bridge>0</Bridge>
    <OCR>0</OCR>
    <Binary>0</Binary>
    <Color>2</Color>
    <Height>0</Height>
    <LiftedLead>0</LiftedLead>
    <ChipChecker>0</ChipChecker>
    <ResistorColorChecker>0</ResistorColorChecker>
    <BridgeOffset>0</BridgeOffset>
    <ChipColorInsp>0</ChipColorInsp>
    <ICSolder>0</ICSolder>
    <ContoursFind>0</ContoursFind>
  </DefectCount>

  <InspCount>
    <Part>257</Part>
    <Frame>5</Frame>
    <Window>1169</Window>
    <Mounting>322</Mounting>
    <Solder>509</Solder>
    <Bridge>32</Bridge>
    <OCR>0</OCR>
    <Binary>0</Binary>
    <Color>218</Color>
    <Height>88</Height>
    <LiftedLead>0</LiftedLead>
    <ChipChecker>0</ChipChecker>
    <ResistorColorChecker>0</ResistorColorChecker>
    <BridgeOffset>0</BridgeOffset>
    <ChipColorInsp>0</ChipColorInsp>
    <ICSolder>0</ICSolder>
    <ContoursFind>0</ContoursFind>
    <PinHole>0</PinHole>
    <SkipInfo>0</SkipInfo>
  </InspCount>

  <ModuleResult>
    <Module IsSkiped="0" ModuleId="1" Result="0"/>
  </ModuleResult>

  <Defect>
    <Overkill>1</Overkill>
    <DefectTypeString>WrongPart</DefectTypeString>
    <ModuleId>1</ModuleId>
    <RefId>C206</RefId>
    <FrameId>2</FrameId>
    <WindowId>2</WindowId>
    <IsImportantWindow>0</IsImportantWindow>
    <PartNumber>10006777-00</PartNumber>
    <PartID>FFC138EE-6481-46da-BEBD-682C0BD8140D</PartID>
    <WindowType>8</WindowType>
    <ViewType>1</ViewType>
    <PartGrabType>-1</PartGrabType>
    <Reviewed>2</Reviewed>
    <GroupDefectInfo>1</GroupDefectInfo>
    <VirtualRefID>V68D0EFEC-E4F6-4739-9048-165707FB498B</VirtualRefID>
    <WindowRefID>_CLR_20_</WindowRefID>
    <ResultValue>0.000000</ResultValue>
    <CameraNo>-1</CameraNo>
    <PartRect X1="1798" X2="1670" X3="1670" X4="1798" Y1="3204" Y2="3204" Y3="3152" Y4="3152"/>
    <WindowRect X1="1740" X2="1726" X3="1726" X4="1740" Y1="3184" Y2="3184" Y3="3169" Y4="3169"/>
    <FrameRect X1="358220" X2="397264" X3="397264" X4="358220" Y1="42087" Y2="42087" Y3="81178" Y4="81178"/>
    <DefectRect X1="375484" X2="375626" X3="375626" X4="375484" Y1="49281" Y2="49281" Y3="49432" Y4="49432"/>
    <AngleOffset>0.00</AngleOffset>
    <Offset X="0" Y="-4"/>
    <Viewer3DMaxRange>0</Viewer3DMaxRange>
    <ViewerDirection>5</ViewerDirection>
    <WindowAngle>180</WindowAngle>
    <DefectType></DefectType>
    <Defect3DType></Defect3DType>
    <PassDefectType>13</PassDefectType>
    <PassDefect3DType/>
    <DefectPins></DefectPins>
    <OverKillPins></OverKillPins>
    <IsChanged>1</IsChanged></Defect>

  <Defect>
    <Overkill>1</Overkill>
    <DefectTypeString>WrongPart</DefectTypeString>
    <ModuleId>1</ModuleId>
    <RefId>C1085</RefId>
    <FrameId>1</FrameId>
    <WindowId>2</WindowId>
    <IsImportantWindow>0</IsImportantWindow>
    <PartNumber>10006777-00</PartNumber>
    <PartID>FFC138EE-6481-46da-BEBD-682C0BD8140D</PartID>
    <WindowType>8</WindowType>
    <ViewType>1</ViewType>
    <PartGrabType>-1</PartGrabType>
    <Reviewed>2</Reviewed>
    <GroupDefectInfo>1</GroupDefectInfo>
    <VirtualRefID>V957D0A3A-1890-4c02-AE09-7D417022026D</VirtualRefID>
    <WindowRefID>_CLR_16_</WindowRefID>
    <ResultValue>0.000000</ResultValue>
    <CameraNo>-1</CameraNo>
    <PartRect X1="1919" X2="1791" X3="1791" X4="1919" Y1="2280" Y2="2280" Y3="2228" Y4="2228"/>
    <WindowRect X1="1861" X2="1847" X3="1847" X4="1861" Y1="2260" Y2="2260" Y3="2245" Y4="2245"/>
    <FrameRect X1="332605" X2="371648" X3="371648" X4="332605" Y1="45067" Y2="45067" Y3="84157" Y4="84157"/>
    <DefectRect X1="351079" X2="351222" X3="351222" X4="351079" Y1="61511" Y2="61511" Y3="61662" Y4="61662"/>
    <AngleOffset>0.00</AngleOffset>
    <Offset X="1" Y="-5"/>
    <Viewer3DMaxRange>0</Viewer3DMaxRange>
    <ViewerDirection>5</ViewerDirection>
    <WindowAngle>180</WindowAngle>
    <DefectType></DefectType>
    <Defect3DType></Defect3DType>
    <PassDefectType>13</PassDefectType>
    <PassDefect3DType/>
    <DefectPins></DefectPins>
    <OverKillPins></OverKillPins>
    <IsChanged>1</IsChanged></Defect>

</InspData>
